{
  "replace":false,
  "values": [
    {"id":"feywild:mandrake","required":false},
    {"id":"minecolonies:chicken_broth","required":false},
    {"id":"minecolonies:cooked_rice","required":false},
    {"id":"minecolonies:durum","required":false},
    {"id":"minecolonies:pottage","required":false},
    {"id":"minecolonies:rice_ball","required":false},
    {"id":"minecolonies:veggie_quiche","required":false},
    {"id":"pamhc2foodcore:applejellytoastitem","required":false},
    {"id":"pamhc2foodcore:appleyogurtitem","required":false},
    {"id":"pamhc2foodcore:carrotdonutitem","required":false},
    {"id":"pamhc2foodcore:chickennuggetitem","required":false},
    {"id":"pamhc2foodcore:cookedgroundchickenitem","required":false},
    {"id":"pamhc2foodcore:cookiesandmilkitem","required":false},
    {"id":"pamhc2foodcore:fishsticksitem","required":false},
    {"id":"pamhc2foodcore:glowberryjellytoastitem","required":false},
    {"id":"pamhc2foodcore:powdereddonutitem","required":false},
    {"id":"pamhc2foodcore:sprinklesdonutitem","required":false},
    {"id":"pamhc2foodextended:apricotyogurtitem","required":false},
    {"id":"pamhc2foodextended:blackberryjellytoastitem","required":false},
    {"id":"pamhc2foodextended:blueberryjellytoastitem","required":false},
    {"id":"pamhc2foodextended:bratwurstitem","required":false},
    {"id":"pamhc2foodextended:bulgogiitem","required":false},
    {"id":"pamhc2foodextended:cactusfruitjellytoastitem","required":false},
    {"id":"pamhc2foodextended:candleberryjellytoastitem","required":false},
    {"id":"pamhc2foodextended:candleberryyogurtitem","required":false},
    {"id":"pamhc2foodextended:cheesedanishitem","required":false},
    {"id":"pamhc2foodextended:cheesytacotortillachipsitem","required":false},
    {"id":"pamhc2foodextended:cherrysmoothieitem","required":false},
    {"id":"pamhc2foodextended:cherryyogurtitem","required":false},
    {"id":"pamhc2foodextended:chilipoppersitem","required":false},
    {"id":"pamhc2foodextended:chocolatemilkshakeitem","required":false},
    {"id":"pamhc2foodextended:cinnamonsugardonutitem","required":false},
    {"id":"pamhc2foodextended:cornishpastyitem","required":false},
    {"id":"pamhc2foodextended:dragonfruitjellytoastitem","required":false},
    {"id":"pamhc2foodextended:driedsoupitem","required":false},
    {"id":"pamhc2foodextended:elderberrysmoothieitem","required":false},
    {"id":"pamhc2foodextended:friedriceitem","required":false},
    {"id":"pamhc2foodextended:frosteddonutitem","required":false},
    {"id":"pamhc2foodextended:gourmetporkpattyitem","required":false},
    {"id":"pamhc2foodextended:grapefruitjellytoastitem","required":false},
    {"id":"pamhc2foodextended:grapefruityogurtitem","required":false},
    {"id":"pamhc2foodextended:grapesmoothieitem","required":false},
    {"id":"pamhc2foodextended:grapeyogurtitem","required":false},
    {"id":"pamhc2foodextended:greengrapejellysandwichitem","required":false},
    {"id":"pamhc2foodextended:guavasmoothieitem","required":false},
    {"id":"pamhc2foodextended:guavayogurtitem","required":false},
    {"id":"pamhc2foodextended:hamsweetpicklesandwichitem","required":false},
    {"id":"pamhc2foodextended:mangoyogurtitem","required":false},
    {"id":"pamhc2foodextended:mulberryyogurtitem","required":false},
    {"id":"pamhc2foodextended:mushroomlasagnaitem","required":false},
    {"id":"pamhc2foodextended:passionfruitsmoothieitem","required":false},
    {"id":"pamhc2foodextended:pawpawyogurtitem","required":false},
    {"id":"pamhc2foodextended:peachjellysandwichitem","required":false},
    {"id":"pamhc2foodextended:peachjellytoastitem","required":false},
    {"id":"pamhc2foodextended:pearyogurtitem","required":false},
    {"id":"pamhc2foodextended:persimmonsmoothieitem","required":false},
    {"id":"pamhc2foodextended:phoitem","required":false},
    {"id":"pamhc2foodextended:pineapplejellytoastitem","required":false},
    {"id":"pamhc2foodextended:pomegranatesmoothieitem","required":false},
    {"id":"pamhc2foodextended:pomegranateyogurtitem","required":false},
    {"id":"pamhc2foodextended:powdereddonutitem","required":false},
    {"id":"pamhc2foodextended:salisburysteakitem","required":false},
    {"id":"pamhc2foodextended:sausagebeanmeltitem","required":false},
    {"id":"pamhc2foodextended:soursopjellytoastitem","required":false},
    {"id":"pamhc2foodextended:soursopsmoothieitem","required":false},
    {"id":"pamhc2foodextended:springrollitem","required":false},
    {"id":"pamhc2foodextended:starfruitjellysandwichitem","required":false},
    {"id":"pamhc2foodextended:strawberryjellysandwichitem","required":false},
    {"id":"pamhc2foodextended:tamarindsmoothieitem","required":false}
  ]
}