{
  "replace":false,
  "values": [
    {"id":"pamhc2foodcore:caramelicecreamitem","required":false},
    {"id":"pamhc2foodcore:caramelpieitem","required":false},
    {"id":"pamhc2foodcore:chocolatemuffinitem","required":false},
    {"id":"pamhc2foodcore:chocolatepieitem","required":false},
    {"id":"pamhc2foodcore:chorusmuffinitem","required":false},
    {"id":"pamhc2foodcore:fruitpunchitem","required":false},
    {"id":"pamhc2foodcore:sweetberrypieitem","required":false},
    {"id":"pamhc2foodextended:babaganoushitem","required":false},
    {"id":"pamhc2foodextended:bbqjackfruititem","required":false},
    {"id":"pamhc2foodextended:blackberrycobbleritem","required":false},
    {"id":"pamhc2foodextended:blackberrypieitem","required":false},
    {"id":"pamhc2foodextended:breadfruitjuiceitem","required":false},
    {"id":"pamhc2foodextended:carrotjuiceitem","required":false},
    {"id":"pamhc2foodextended:cashewchickenitem","required":false},
    {"id":"pamhc2foodextended:cherryjellyitem","required":false},
    {"id":"pamhc2foodextended:cinnamonrollitem","required":false},
    {"id":"pamhc2foodextended:cookedtofabbititem","required":false},
    {"id":"pamhc2foodextended:cookedtofaconitem","required":false},
    {"id":"pamhc2foodextended:cookedtofishitem","required":false},
    {"id":"pamhc2foodextended:cranberrypieitem","required":false},
    {"id":"pamhc2foodextended:crispyricepuffcerealitem","required":false},
    {"id":"pamhc2foodextended:datejuiceitem","required":false},
    {"id":"pamhc2foodextended:datepieitem","required":false},
    {"id":"pamhc2foodextended:durianjuiceitem","required":false},
    {"id":"pamhc2foodextended:figjellyitem","required":false},
    {"id":"pamhc2foodextended:figpieitem","required":false},
    {"id":"pamhc2foodextended:garlicbreaditem","required":false},
    {"id":"pamhc2foodextended:gooseberrypieitem","required":false},
    {"id":"pamhc2foodextended:gritsitem","required":false},
    {"id":"pamhc2foodextended:guavajellyitem","required":false},
    {"id":"pamhc2foodextended:hotsauceitem","required":false},
    {"id":"pamhc2foodextended:imagawayakiitem","required":false},
    {"id":"pamhc2foodextended:jackfruitpieitem","required":false},
    {"id":"pamhc2foodextended:jellyrollitem","required":false},
    {"id":"pamhc2foodextended:lambwithmintsauceitem","required":false},
    {"id":"pamhc2foodextended:lemonjuiceitem","required":false},
    {"id":"pamhc2foodextended:lemonmeringueitem","required":false},
    {"id":"pamhc2foodextended:mochaicecreamitem","required":false},
    {"id":"pamhc2foodextended:mozzerellasticksitem","required":false},
    {"id":"pamhc2foodextended:orangejellyitem","required":false},
    {"id":"pamhc2foodextended:ovenroastedcaulifloweritem","required":false},
    {"id":"pamhc2foodextended:papayajellyitem","required":false},
    {"id":"pamhc2foodextended:peanutchocolatebaritem","required":false},
    {"id":"pamhc2foodextended:raspberryjuiceitem","required":false},
    {"id":"pamhc2foodextended:roastedrootveggiemedleyitem","required":false},
    {"id":"pamhc2foodextended:sausageitem","required":false},
    {"id":"pamhc2foodextended:spinachpieitem","required":false},
    {"id":"pamhc2foodextended:starfruitjellyitem","required":false},
    {"id":"pamhc2foodextended:strawberrypieitem","required":false},
    {"id":"pamhc2foodextended:surfandturfitem","required":false},
    {"id":"pamhc2foodextended:sweetteaitem","required":false},
    {"id":"pamhc2foodextended:tamarindjellyitem","required":false},
    {"id":"pamhc2foodextended:toastedwesternitem","required":false}
  ]
}