{
  "base_gear": "sword",
  "flavor_text": "",
  "force_item_id": "roe_weapons:sword_7",
  "guid": "glacial_sword",
  "league": "",
  "min_drop_lvl": 1,
  "min_tier": 0,
  "rarity": "unique",
  "replaces_name": true,
  "runable": false,
  "unique_stats": [
    {
      "type": "PERCENT",
      "max": 91.0,
      "min": 35.0,
      "stat": "gear_weapon_damage"
    },
    {
      "type": "PERCENT",
      "max": 16.0,
      "min": 8.0,
      "stat": "armor"
    },
    {
      "type": "PERCENT",
      "max": 15.0,
      "min": 8.0,
      "stat": "melee_cdr"
    },
    {
      "type": "PERCENT",
      "max": 14.0,
      "min": 8.0,
      "stat": "critical_damage"
    },
    {
      "type": "PERCENT",
      "max": 17.0,
      "min": 11.0,
      "stat": "lifesteal"
    },
    {
      "type": "FLAT",
      "max": 20.0,
      "min": 10.0,
      "stat": "all_water_damage"
    }
  ],
  "weight": 1000
}