{
	"size": "small",
	"color": "#8000ff",
	"waves": [{
			"entities": [
				{ 
					"entity": "minecraft:slime",
					"count": 1
				},
				{
					"entity": "tconstruct:sky_slime",
					"count": 1
				}
			],
			"rewards": [],
			"max_wave_time": 1200,
			"setup_time": 60
		},
		{
			"entities": [
				{
					"entity": "minecraft:slime",
					"count": 1
				},
				{
					"entity": "tconstruct:sky_slime",
					"count": 1
				}
			],
			"rewards": [],
			"max_wave_time": 1200,
			"setup_time": 60
		},
		{
			"entities": [
				{
					"entity": "minecraft:slime",
					"count": 1
				},
				{
					"entity": "tconstruct:ender_slime",
					"count": 1
				}
			],
			"rewards": [],
			"max_wave_time": 1200,
			"setup_time": 60
		},
		{
			"entities": [
				{
					"entity": "minecraft:slime",
					"count": 1
				},
				{
					"entity": "tconstruct:sky_slime",
					"count": 1
				},
				{
					"entity": "tconstruct:ender_slime",
					"count": 1
				}
			],
			"rewards": [],
			"max_wave_time": 1800,
			"setup_time": 60
		}
	],
    "rewards": [
        {
            "type": "gateways:loot_table",
            "loot_table": "p3:p3_gateways",
            "rolls": 1,
            "desc": "Basic Reward"
        },
        {
            "type": "gateways:loot_table",
            "loot_table": "p3:p3_epic",
            "rolls": 1,
            "desc": "Epic Reward"
        }
    ],
    "failures": [
    ],
    "rules": {
        "spawn_range": 4,
        "leash_range": 16,
        "spacing": 100
    }
}